.gitignore
LICENSE
README.md
noxfile.py
requirements.txt
setup.py
.github/workflows/publish.yaml
.github/workflows/tests.yaml
lucious/__init__.py
lucious/frozone.py
lucious/types.py
lucious/utils.py
lucious.egg-info/PKG-INFO
lucious.egg-info/SOURCES.txt
lucious.egg-info/dependency_links.txt
lucious.egg-info/top_level.txt
tests/__init__.py
tests/lucious/__init__.py
tests/lucious/frozone_test.py
tests/lucious/utils_test.py
tests/lucious/types/QualifiedTableName_test.py
tests/lucious/types/SnowflakeColumn_test.py
tests/lucious/types/SnowflakeTable_test.py
tests/lucious/types/__init__.py