Metadata-Version: 2.1
Name: lucious
Version: 0.1.2
Summary: a chill tool for dealing with Snowflake
Home-page: https://github.com/withtwoemms/lucious
Author: Emmanuel I. Obi
Maintainer: Emmanuel I. Obi
Maintainer-email: withtwoemms@gmail.com
License: UNKNOWN
Platform: UNKNOWN
Classifier: Development Status :: 1 - Planning
Classifier: Intended Audience :: Developers
Classifier: Intended Audience :: Education
Classifier: Intended Audience :: Science/Research
Classifier: Topic :: Software Development :: Build Tools
Classifier: License :: OSI Approved :: MIT License
Classifier: Programming Language :: Python :: 3.7
Classifier: Programming Language :: Python :: 3.8
Classifier: Programming Language :: Python :: 3.9
Classifier: Programming Language :: Python :: 3.10
License-File: LICENSE
